{
  "台帳ID": "101",
  "管理対象ID": "00004065",
  "名称": "橋本家住宅石垣及び塀",
  "ふりがな": "はしもとけじゅうたくいしがきおよびへい",
  "員数": "1棟",
  "棟名": "はしもとけじゅうたくいしがきおよびへい",
  "文化財種類": "1棟",
  "種別1": "",
  "種別2": "登録有形文化財(建造物)",
  "国": "住宅",
  "時代": "その他工作",
  "年代": "昭和初期",
  "西暦": "1926-1988",
  "構造及び形式等": "鉄筋コンクリート造、延長22m",
  "その他参考となるべき事項": "",
  "登録番号": "39 － 0133",
  "登録回": "41",
  "登録告示年月日": "2004.03.29(平成16.03.29)",
  "登録年月日": "2004.03.02(平成16.03.02)",
  "追加年月日": "",
  "重文指定年月日": "",
  "国宝指定年月日": "昭和前",
  "登録基準1": "国土の歴史的景観に寄与しているもの",
  "登録基準2": "",
  "都道府県": "昭和初期",
  "所在地": "1926-1988",
  "保管施設の名称": "鉄筋コンクリート造、延長22m",
  "所有者名": "",
  "所有者種別": "",
  "管理団体又は責任者": "39 － 0133",
  "緯度": "41",
  "経度": "2004.03.29(平成16.03.29)",
  "解説文": "道路から一段上がった屋敷地までの石垣とその上に築かれた門柱及び塀。石垣はやや大振りの川石で築き，塀は高さ０．９ｍ，門柱は０．２３ｍ角，高１．８３ｍのＲＣ造。塀に貝文と七宝文の浮彫模様を格間毎交互に描いているのが特徴で，地域で目立つ存在。",
  "画像URL": "https://bunka.nii.ac.jp/heritage/43967/_105055/43967_105055111225014629304_300.jpg"
}