{
  "台帳ID": "101",
  "管理対象ID": "00004233",
  "名称": "アカタン砂防大平ナベカマ堰堤",
  "ふりがな": "あかたんさぼうおおびらなべかまえんてい",
  "員数": "1基",
  "棟名": "あかたんさぼうおおびらなべかまえんてい",
  "文化財種類": "1基",
  "種別1": "",
  "種別2": "登録有形文化財(建造物)",
  "国": "治山治水",
  "時代": "土木構造物",
  "年代": "明治30代",
  "西暦": "1897-1906",
  "構造及び形式等": "石造堰堤、堤長6.0m、堤高3.0m",
  "その他参考となるべき事項": "",
  "登録番号": "18 － 0030",
  "登録回": "43",
  "登録告示年月日": "2004.08.17(平成16.08.17)",
  "登録年月日": "2004.07.23(平成16.07.23)",
  "追加年月日": "",
  "重文指定年月日": "",
  "国宝指定年月日": "明治",
  "登録基準1": "国土の歴史的景観に寄与しているもの",
  "登録基準2": "",
  "都道府県": "明治30代",
  "所在地": "1897-1906",
  "保管施設の名称": "石造堰堤、堤長6.0m、堤高3.0m",
  "所有者名": "",
  "所有者種別": "",
  "管理団体又は責任者": "18 － 0030",
  "緯度": "43",
  "経度": "2004.08.17(平成16.08.17)",
  "解説文": "大平中堰堤の約９０ｍ下流に位置する。露出した岩盤上に築かれた堤長６．０ｍ，堤高３．０ｍ，約１割法の小規模かつ緩勾配の空石積堰堤で，堤頂を縄弛みさせる。渓岸の浸食と崩壊を防ぎ，渓床勾配の緩和に効果を発揮することで，周囲の自然緑化を導いている。",
  "画像URL": "https://bunka.nii.ac.jp/heritage/43967/_105223/43967_105223111225014811562_300.jpg"
}