{
  "台帳ID": "101",
  "管理対象ID": "00009569",
  "名称": "旧岡田家住宅主屋",
  "ふりがな": "きゅうおかだけじゅうたくしゅおく",
  "員数": "1棟",
  "棟名": "きゅうおかだけじゅうたくしゅおく",
  "文化財種類": "1棟",
  "種別1": "",
  "種別2": "登録有形文化財(建造物)",
  "国": "住宅",
  "時代": "建築物",
  "年代": "昭和8／平成23改修",
  "西暦": "1933／2011改修",
  "構造及び形式等": "木造2階建、鉄板葺、建築面積339㎡",
  "その他参考となるべき事項": "",
  "登録番号": "01 － 0132",
  "登録回": "75",
  "登録告示年月日": "2013.06.21(平成25.06.21)",
  "登録年月日": "2013.06.21(平成25.06.21)",
  "追加年月日": "",
  "重文指定年月日": "",
  "国宝指定年月日": "昭和前",
  "登録基準1": "造形の規範となっているもの",
  "登録基準2": "",
  "都道府県": "昭和8／平成23改修",
  "所在地": "1933／2011改修",
  "保管施設の名称": "木造2階建、鉄板葺、建築面積339㎡",
  "所有者名": "",
  "所有者種別": "その他",
  "管理団体又は責任者": "01 － 0132",
  "緯度": "75",
  "経度": "2013.06.21(平成25.06.21)",
  "解説文": "旭川市街に建つ酒造家の本邸。木造二階建で北から西に敷地を囲み、入隅に四半円形の居間を設ける。外観は洋風であるが玄関ホールや応接室の他は数寄屋風の座敷とする。玄関のステンドグラス、西側階段室の縦長窓と階段などにアール・デコ風の意匠を凝らす。",
  "画像URL": "https://bunka.nii.ac.jp/heritage/43967/_194565/43967_194565140916101142200_300.jpg"
}