{
  "台帳ID": "101",
  "管理対象ID": "00002070",
  "名称": "杉田家住宅蔵",
  "ふりがな": "すぎたけじゅうたくくら",
  "員数": "1棟",
  "棟名": "",
  "文化財種類": "登録有形文化財(建造物)",
  "種別1": "住宅",
  "種別2": "建築物",
  "国": "",
  "時代": "昭和前",
  "年代": "昭和4",
  "西暦": "1929",
  "構造及び形式等": "土蔵造2階建、瓦葺、建築面積29㎡",
  "その他参考となるべき事項": "",
  "登録番号": "27 － 0131",
  "登録回": "27",
  "登録告示年月日": "2000.12.20(平成12.12.20)",
  "登録年月日": "2000.12.04(平成12.12.04)",
  "追加年月日": "",
  "重文指定年月日": "20001204",
  "国宝指定年月日": "",
  "登録基準1": "再現することが容易でないもの",
  "登録基準2": "",
  "都道府県": "大阪府",
  "所在地": "大阪府富田林市本町5-13",
  "保管施設の名称": "",
  "所有者名": "",
  "所有者種別": "",
  "管理団体又は責任者": "",
  "緯度": "34.50261000000000",
  "経度": "135.59900000000000",
  "解説文": "木造，２階建，切妻造，桟瓦葺の建物で，敷地の南端部に位置し，主屋の奥に蔵前を介して接続する。白壁で大きな軒蛇腹を持つ丁寧な仕事になる伝統的な土蔵造で，立ちの高い外観は洋風の主屋と好対照をなし，屋敷構えを整える重要な要素となる。",
  "画像URL": "https://bunka.nii.ac.jp/heritage/43967/_103060/43967_103060111225012518764_300.jpg"
}