{
  "台帳ID": "101",
  "管理対象ID": "00000560",
  "名称": "舞鶴橋",
  "ふりがな": "まいづるばし",
  "員数": "1基",
  "棟名": "",
  "文化財種類": "登録有形文化財(建造物)",
  "種別1": "文化福祉",
  "種別2": "土木構造物",
  "国": "",
  "時代": "明治",
  "年代": "明治19",
  "西暦": "1886",
  "構造及び形式等": "石造アーチ橋，橋長５m，幅員７m",
  "その他参考となるべき事項": "",
  "登録番号": "06 － 0028",
  "登録回": "10",
  "登録告示年月日": "1998.08.04(平成10.08.04)",
  "登録年月日": "1998.07.23(平成10.07.23)",
  "追加年月日": "",
  "重文指定年月日": "19980723",
  "国宝指定年月日": "",
  "登録基準1": "国土の歴史的景観に寄与しているもの",
  "登録基準2": "",
  "都道府県": "山形県",
  "所在地": "山形県米沢市丸の内1-4-13",
  "保管施設の名称": "",
  "所有者名": "米沢市",
  "所有者種別": "",
  "管理団体又は責任者": "",
  "緯度": "37.90889000000000",
  "経度": "140.10590000000000",
  "解説文": "米沢城祉の堀に架かる石造橋で，現在は上杉神社への参道となっている。径間に比して幅員が広く，凝灰岩の欄干を設け親柱に自然石の奇岩を配するのが特徴。単アーチ橋ではあるが，「めがね橋」の愛称で米沢市民に広く親しまれている。",
  "画像URL": "https://bunka.nii.ac.jp/heritage/43967/_101550/43967_101550111225010847371_300.jpg"
}