{
  "台帳ID": "101",
  "管理対象ID": "00008253",
  "名称": "上野家住宅離屋",
  "ふりがな": "うえのけじゅうたくはなれや",
  "員数": "1棟",
  "棟名": "うえのけじゅうたくはなれや",
  "文化財種類": "1棟",
  "種別1": "",
  "種別2": "登録有形文化財(建造物)",
  "国": "住宅",
  "時代": "建築物",
  "年代": "大正6年",
  "西暦": "1917",
  "構造及び形式等": "土蔵造平屋建、瓦葺、建築面積46㎡",
  "その他参考となるべき事項": "",
  "登録番号": "07 － 0115",
  "登録回": "68",
  "登録告示年月日": "2010.09.10(平成22.09.10)",
  "登録年月日": "2010.09.10(平成22.09.10)",
  "追加年月日": "",
  "重文指定年月日": "",
  "国宝指定年月日": "大正",
  "登録基準1": "造形の規範となっているもの",
  "登録基準2": "",
  "都道府県": "大正6年",
  "所在地": "1917",
  "保管施設の名称": "土蔵造平屋建、瓦葺、建築面積46㎡",
  "所有者名": "",
  "所有者種別": "",
  "管理団体又は責任者": "07 － 0115",
  "緯度": "68",
  "経度": "2010.09.10(平成22.09.10)",
  "解説文": "主屋の西南に位置し、東面に庭を設ける。南北棟の入母屋造桟瓦葺で、西面に角屋を設けて浴室や便所とする。十畳の一室で、縁を付設し、西面にトコや棚を構える。紫檀や欅、縞柿などの銘木を用い、山水や鶴などの襖絵を飾る。近代における良質な接客空間の一例。",
  "画像URL": "https://bunka.nii.ac.jp/heritage/43967/_133895/43967_133895111225033405784_300.jpg"
}