{
  "台帳ID": "101",
  "管理対象ID": "00001399",
  "名称": "長者滝橋",
  "ふりがな": "ちょうじゃたきばし",
  "員数": "1基",
  "棟名": "ちょうじゃたきばし",
  "文化財種類": "1基",
  "種別1": "",
  "種別2": "登録有形文化財(建造物)",
  "国": "交通",
  "時代": "土木構造物",
  "年代": "昭和14",
  "西暦": "1939",
  "構造及び形式等": "コンクリート造2連アーチ橋、鉄筋コンクリート造取付桁橋附属、橋長61m、幅員3.9m",
  "その他参考となるべき事項": "",
  "登録番号": "03 － 0031",
  "登録回": "21",
  "登録告示年月日": "1999.12.02(平成11.12.02)",
  "登録年月日": "1999.11.18(平成11.11.18)",
  "追加年月日": "",
  "重文指定年月日": "",
  "国宝指定年月日": "昭和前",
  "登録基準1": "国土の歴史的景観に寄与しているもの",
  "登録基準2": "",
  "都道府県": "昭和14",
  "所在地": "1939",
  "保管施設の名称": "コンクリート造2連アーチ橋、鉄筋コンクリート造取付桁橋附属、橋長61m、幅員3.9m",
  "所有者名": "",
  "所有者種別": "",
  "管理団体又は責任者": "03 － 0031",
  "緯度": "21",
  "経度": "1999.12.02(平成11.12.02)",
  "解説文": "磐井川に架設された竹筋入りコンクリート橋。径間１８ｍの中央２連アーチ部と左右各２側径間部からなる。充腹アーチの重厚な趣に加えて，橋台・橋脚が岩盤に定着されることで，名勝天然記念物に指定された厳美渓に溶け込んだ景観を創り出している。",
  "画像URL": "https://bunka.nii.ac.jp/heritage/43967/_102389/43967_102389111225011756739_300.jpg"
}