{
  "台帳ID": "101",
  "管理対象ID": "00003136",
  "名称": "大谷焼元山窯水簸場",
  "ふりがな": "おおたにやきもとやまがますいひば",
  "員数": "1棟",
  "棟名": "",
  "文化財種類": "登録有形文化財(建造物)",
  "種別1": "産業2次",
  "種別2": "その他工作",
  "国": "",
  "時代": "昭和前",
  "年代": "昭和初期",
  "西暦": "1926-1988",
  "構造及び形式等": "煉瓦造及びコンクリート造、面積55㎡",
  "その他参考となるべき事項": "",
  "登録番号": "36 － 0043",
  "登録回": "35",
  "登録告示年月日": "2003.02.26(平成15.02.26)",
  "登録年月日": "2003.01.31(平成15.01.31)",
  "追加年月日": "",
  "重文指定年月日": "20030131",
  "国宝指定年月日": "",
  "登録基準1": "国土の歴史的景観に寄与しているもの",
  "登録基準2": "",
  "都道府県": "徳島県",
  "所在地": "徳島県鳴門市大麻町大谷字山田37",
  "保管施設の名称": "",
  "所有者名": "田村商事株式会社",
  "所有者種別": "",
  "管理団体又は責任者": "",
  "緯度": "34.16286000000000",
  "経度": "134.53760000000000",
  "解説文": "旧藩窯である元山窯の作業場に付属する。粘土を精製して陶土とするための施設で，原土撹拌槽・Ｓ字状の誘水路と沈澄槽・分離槽・４つの沈殿槽から成る。藍瓶など大型焼物用陶土に対応した水簸施設で，大谷焼の製作工程近代化の一端を伝え貴重である。",
  "画像URL": "https://bunka.nii.ac.jp/heritage/43967/_104126/43967_104126111225013619868_300.jpg"
}