{
  "台帳ID": "101",
  "管理対象ID": "00006467",
  "名称": "旧三井田川鉱業所伊田竪坑第一煙突",
  "ふりがな": "きゅうみついたがわこうぎょうしょいだたてこうだいいちえんとつ",
  "員数": "1基",
  "棟名": "きゅうみついたがわこうぎょうしょいだたてこうだいいちえんとつ",
  "文化財種類": "1基",
  "種別1": "",
  "種別2": "登録有形文化財(建造物)",
  "国": "産業2次",
  "時代": "その他工作",
  "年代": "明治41",
  "西暦": "1908",
  "構造及び形式等": "煉瓦造、高さ45m",
  "その他参考となるべき事項": "",
  "登録番号": "40 － 0052",
  "登録回": "56",
  "登録告示年月日": "2007.10.22(平成19.10.22)",
  "登録年月日": "2007.10.02(平成19.10.02)",
  "追加年月日": "",
  "重文指定年月日": "",
  "国宝指定年月日": "明治",
  "登録基準1": "国土の歴史的景観に寄与しているもの",
  "登録基準2": "",
  "都道府県": "明治41",
  "所在地": "1908",
  "保管施設の名称": "煉瓦造、高さ45m",
  "所有者名": "",
  "所有者種別": "",
  "管理団体又は責任者": "40 － 0052",
  "緯度": "56",
  "経度": "2007.10.22(平成19.10.22)",
  "解説文": "竪坑櫓より約１２０ｍ南方に位置する。旧汽罐場に付属する高さ４５ｍ（１５０尺）の煉瓦造円形煙突で、全体をイギリス積で精緻に築き、基部には半円アーチ形の煙道を一部残す。現存する明治期の煉瓦煙突として最大級の規模を誇る。",
  "画像URL": "https://bunka.nii.ac.jp/heritage/43967/_107450/43967_107450111225024115996_300.jpg"
}