{
  "台帳ID": "101",
  "管理対象ID": "00001471",
  "名称": "佐滝文庫蔵",
  "ふりがな": "さたきぶんこぐら",
  "員数": "1棟",
  "棟名": "",
  "文化財種類": "登録有形文化財(建造物)",
  "種別1": "住宅",
  "種別2": "建築物",
  "国": "",
  "時代": "明治",
  "年代": "明治26",
  "西暦": "1893",
  "構造及び形式等": "土蔵造2階建、鉄板葺、建築面積35㎡",
  "その他参考となるべき事項": "",
  "登録番号": "02 － 0012",
  "登録回": "22",
  "登録告示年月日": "2000.03.02(平成12.03.02)",
  "登録年月日": "2000.02.15(平成12.02.15)",
  "追加年月日": "",
  "重文指定年月日": "20000215",
  "国宝指定年月日": "",
  "登録基準1": "再現することが容易でないもの",
  "登録基準2": "",
  "都道府県": "青森県",
  "所在地": "青森県三戸郡三戸町大字八日町49",
  "保管施設の名称": "",
  "所有者名": "",
  "所有者種別": "",
  "管理団体又は責任者": "",
  "緯度": "40.37700000000000",
  "経度": "141.25650000000000",
  "解説文": "佐滝は明治１９年から雑貨商を営んだ商店で，通りに面した店舗が登録されている。文庫蔵は墨書から明治２６年３月竣工とわかり，佐滝で最古の開業当時の建物である。黒漆喰塗・切妻造の小規模なものであるが，軒廻りや観音扉などに高い技術が認められる。",
  "画像URL": "https://bunka.nii.ac.jp/heritage/43967/_102461/43967_102461111225011845351_300.jpg"
}