{
  "台帳ID": "101",
  "管理対象ID": "00006591",
  "名称": "上毛電気鉄道大胡駅変電所",
  "ふりがな": "じょうもうでんきてつどうおおごえきへんでんしょ",
  "員数": "1棟",
  "棟名": "じょうもうでんきてつどうおおごえきへんでんしょ",
  "文化財種類": "1棟",
  "種別1": "",
  "種別2": "登録有形文化財(建造物)",
  "国": "交通",
  "時代": "建築物",
  "年代": "昭和3／昭和18増築",
  "西暦": "1928／1943増築",
  "構造及び形式等": "鉄筋コンクリート造平屋建、建築面積166㎡、地下室及び石垣付",
  "その他参考となるべき事項": "",
  "登録番号": "10 － 0235",
  "登録回": "55",
  "登録告示年月日": "2007.08.13(平成19.08.13)",
  "登録年月日": "2007.07.31(平成19.07.31)",
  "追加年月日": "",
  "重文指定年月日": "",
  "国宝指定年月日": "昭和前",
  "登録基準1": "国土の歴史的景観に寄与しているもの",
  "登録基準2": "",
  "都道府県": "昭和3／昭和18増築",
  "所在地": "1928／1943増築",
  "保管施設の名称": "鉄筋コンクリート造平屋建、建築面積166㎡、地下室及び石垣付",
  "所有者名": "",
  "所有者種別": "",
  "管理団体又は責任者": "10 － 0235",
  "緯度": "55",
  "経度": "2007.08.13(平成19.08.13)",
  "解説文": "駅舎より約７５ｍ南西に位置する。変圧器，整流器等を収容し，交流から直流への変換を行う。建築面積１２２㎡の機器室の北側に，事務室を増築し，当初部分は縦長窓を配し，東妻面に柱形をあしらうつくり。増築部分を含め全体に蛇腹を廻らし外観を整える。",
  "画像URL": "https://bunka.nii.ac.jp/heritage/43967/_107574/43967_107574111225024440799_300.jpg"
}