{
  "台帳ID": "101",
  "管理対象ID": "00006899",
  "名称": "平尾家住宅石垣",
  "ふりがな": "",
  "員数": "1基",
  "棟名": "",
  "文化財種類": "1基",
  "種別1": "",
  "種別2": "登録有形文化財(建造物)",
  "国": "住宅",
  "時代": "その他工作",
  "年代": "江戸後期／明治中期・昭和前期改修",
  "西暦": "1751-1829／1868-1911・1926-1988改修",
  "構造及び形式等": "石造、延長148m",
  "その他参考となるべき事項": "",
  "登録番号": "28 － 0323",
  "登録回": "58",
  "登録告示年月日": "2008.03.19(平成20.03.19)",
  "登録年月日": "2008.03.07(平成20.03.07)",
  "追加年月日": "",
  "重文指定年月日": "",
  "国宝指定年月日": "江戸",
  "登録基準1": "国土の歴史的景観に寄与しているもの",
  "登録基準2": "",
  "都道府県": "江戸後期／明治中期・昭和前期改修",
  "所在地": "1751-1829／1868-1911・1926-1988改修",
  "保管施設の名称": "石造、延長148m",
  "所有者名": "",
  "所有者種別": "",
  "管理団体又は責任者": "28 － 0323",
  "緯度": "58",
  "経度": "2008.03.19(平成20.03.19)",
  "解説文": "屋敷地を南北に２分する森尾川の両岸に築かれた石垣。高さ約１．５ｍで総延長１４８ｍに及ぶ。花崗岩や玄武岩などの切石の谷積や布積のほか、野石積などが見られ、度重なる修復が窺える。川越しに主屋を望む独特の屋敷内景観をつくる。",
  "画像URL": "https://bunka.nii.ac.jp/heritage/43967/_107881/43967_107881111225025253306_300.jpg"
}