{
  "台帳ID": "101",
  "管理対象ID": "00003652",
  "名称": "明治村三重県尋常師範学校・蔵持小学校",
  "ふりがな": "めいじむらみえけんじんじょうしはんがっこう・くらもちしょうがっこう",
  "員数": "1棟",
  "棟名": "",
  "文化財種類": "登録有形文化財(建造物)",
  "種別1": "学校",
  "種別2": "建築物",
  "国": "",
  "時代": "明治",
  "年代": "明治21／昭和48移築",
  "西暦": "1888／1973移築",
  "構造及び形式等": "木造2階建、瓦葺、建築面積365㎡",
  "その他参考となるべき事項": "",
  "登録番号": "23 － 0065",
  "登録回": "39",
  "登録告示年月日": "2003.12.25(平成15.12.25)",
  "登録年月日": "2003.12.01(平成15.12.01)",
  "追加年月日": "",
  "重文指定年月日": "20031201",
  "国宝指定年月日": "",
  "登録基準1": "造形の規範となっているもの",
  "登録基準2": "",
  "都道府県": "愛知県",
  "所在地": "愛知県犬山市内山1博物館明治村内",
  "保管施設の名称": "",
  "所有者名": "公益財団法人明治村",
  "所有者種別": "",
  "管理団体又は責任者": "",
  "緯度": "35.34014000000000",
  "経度": "136.98790000000000",
  "解説文": "木造２階建，桟瓦葺，外壁は玄関部が漆喰塗，教室部が下見板張。軒先持送りと胴蛇腹の下に飾りパネルを付け，簡素な上げ下げ窓を配す。玄関部と１階廊下にトスカナ式円柱を配し，入母屋破風とポーチ扁平アーチを植物意匠で飾る。設計は三重県技師の清水義八。",
  "画像URL": "https://bunka.nii.ac.jp/heritage/43967/_104642/43967_104642111225014146866_300.jpg"
}