{
  "台帳ID": "101",
  "管理対象ID": "00002189",
  "名称": "北海道林木育種場旧庁舎",
  "ふりがな": "ほっかいどうりんぼくいくしゅじょうきゅうちょうしゃ",
  "員数": "1棟",
  "棟名": "",
  "文化財種類": "登録有形文化財(建造物)",
  "種別1": "産業1次",
  "種別2": "建築物",
  "国": "",
  "時代": "昭和前",
  "年代": "昭和2",
  "西暦": "1927",
  "構造及び形式等": "木造2階建、鉄板葺、建築面積744㎡",
  "その他参考となるべき事項": "",
  "登録番号": "01 － 0030",
  "登録回": "29",
  "登録告示年月日": "2001.09.14(平成13.09.14)",
  "登録年月日": "2001.08.28(平成13.08.28)",
  "追加年月日": "",
  "重文指定年月日": "20010828",
  "国宝指定年月日": "",
  "登録基準1": "国土の歴史的景観に寄与しているもの",
  "登録基準2": "",
  "都道府県": "北海道",
  "所在地": "北海道江別市文京台緑町561-1",
  "保管施設の名称": "",
  "所有者名": "江別市",
  "所有者種別": "",
  "管理団体又は責任者": "",
  "緯度": "43.07852000000000",
  "経度": "141.52030000000000",
  "解説文": "野幌森林公園内の北端部にある。北海道庁林業試験場として建設される。1階を煉瓦組積造，2階をハーフティンバー風木造とし，外装モルタル洗出とする。小屋組はクイーンポストトラス風。市の高台に位置し，地域のランドマークとして親しまれている。",
  "画像URL": "https://bunka.nii.ac.jp/heritage/43967/_103179/43967_103179111225012634166_300.jpg"
}