{
  "台帳ID": "101",
  "管理対象ID": "00007752",
  "名称": "アンドリュース記念館（旧近江八幡ＹＭＣＡ会館）",
  "ふりがな": "あんどりゅーすきねんかん（きゅうおうみはちまんわいえむしーえーかいかん）",
  "員数": "1棟",
  "棟名": "あんどりゅーすきねんかん（きゅうおうみはちまんわいえむしーえーかいかん）",
  "文化財種類": "1棟",
  "種別1": "",
  "種別2": "登録有形文化財(建造物)",
  "国": "文化福祉",
  "時代": "建築物",
  "年代": "昭和10／平成19改修",
  "西暦": "1935／2007改修",
  "構造及び形式等": "木造2階建、瓦葺、建築面積161㎡",
  "その他参考となるべき事項": "",
  "登録番号": "25-0277",
  "登録回": "64",
  "登録告示年月日": "2009.08.25(平成21.08.25)",
  "登録年月日": "2009.08.07(平成21.08.07)",
  "追加年月日": "",
  "重文指定年月日": "",
  "国宝指定年月日": "昭和前",
  "登録基準1": "国土の歴史的景観に寄与しているもの",
  "登録基準2": "",
  "都道府県": "昭和10／平成19改修",
  "所在地": "1935／2007改修",
  "保管施設の名称": "木造2階建、瓦葺、建築面積161㎡",
  "所有者名": "",
  "所有者種別": "",
  "管理団体又は責任者": "25-0277",
  "緯度": "64",
  "経度": "2009.08.25(平成21.08.25)",
  "解説文": "八幡山東南の市街地に位置する。桁行１５ｍ梁間１１ｍの木造２階建、南北棟の入母屋造桟瓦葺。２階は南寄りに和室二室、北に洋室二室を並べ、中央を階段室等とする。釉薬瓦の赤とモルタル仕上げ壁の白が好対照をなし、親しみのある佇まいを見せる。",
  "画像URL": "https://bunka.nii.ac.jp/heritage/43967/_108733/43967_108733111225031923113_300.jpg"
}