{
  "台帳ID": "101",
  "管理対象ID": "00001710",
  "名称": "清水寺鐘楼",
  "ふりがな": "きよみずでらしょうろう",
  "員数": "1棟",
  "棟名": "きよみずでらしょうろう",
  "文化財種類": "1棟",
  "種別1": "",
  "種別2": "登録有形文化財(建造物)",
  "国": "宗教",
  "時代": "建築物",
  "年代": "大正8",
  "西暦": "1919",
  "構造及び形式等": "木造平屋建、瓦葺、建築面積27㎡",
  "その他参考となるべき事項": "",
  "登録番号": "22 － 0068",
  "登録回": "24",
  "登録告示年月日": "2000.05.25(平成12.05.25)",
  "登録年月日": "2000.04.28(平成12.04.28)",
  "追加年月日": "",
  "重文指定年月日": "",
  "国宝指定年月日": "大正",
  "登録基準1": "造形の規範となっているもの",
  "登録基準2": "",
  "都道府県": "大正8",
  "所在地": "1919",
  "保管施設の名称": "木造平屋建、瓦葺、建築面積27㎡",
  "所有者名": "",
  "所有者種別": "",
  "管理団体又は責任者": "22 － 0068",
  "緯度": "24",
  "経度": "2000.05.25(平成12.05.25)",
  "解説文": "方一間、四方吹き放しの鐘台で、屋根は入母屋造、本瓦葺とする。本柱と間柱上に尾垂木付の組物を置いて華やかな軒廻りとする。青銅鋳物製の隅支柱に蓮をモチーフとする意匠を施し、蟇股や木鼻の意匠にも特色がある。設計は東京美術学校の古宇田實。",
  "画像URL": "https://bunka.nii.ac.jp/heritage/43967/_102700/43967_102700111225012118377_300.jpg"
}