{
  "台帳ID": "101",
  "管理対象ID": "00002765",
  "名称": "木和田川砂防二号堰堤",
  "ふりがな": "きわだがわさぼうにごうえんてい",
  "員数": "1基",
  "棟名": "きわだがわさぼうにごうえんてい",
  "文化財種類": "1基",
  "種別1": "",
  "種別2": "登録有形文化財(建造物)",
  "国": "治山治水",
  "時代": "土木構造物",
  "年代": "大正1頃",
  "西暦": "1912頃",
  "構造及び形式等": "石造堰堤、堤長27m、堤高5.8m、水叩き部及び下流両側護岸9m付",
  "その他参考となるべき事項": "",
  "登録番号": "22 － 0081",
  "登録回": "33",
  "登録告示年月日": "2002.07.16(平成14.07.16)",
  "登録年月日": "2002.06.25(平成14.06.25)",
  "追加年月日": "",
  "重文指定年月日": "",
  "国宝指定年月日": "大正",
  "登録基準1": "国土の歴史的景観に寄与しているもの",
  "登録基準2": "",
  "都道府県": "大正1頃",
  "所在地": "1912頃",
  "保管施設の名称": "石造堰堤、堤長27m、堤高5.8m、水叩き部及び下流両側護岸9m付",
  "所有者名": "",
  "所有者種別": "",
  "管理団体又は責任者": "22 － 0081",
  "緯度": "33",
  "経度": "2002.07.16(平成14.07.16)",
  "解説文": "一号堰堤の北東約１３０ｍ上流側に位置する。堤高５．８ｍ，法面勾配１割２分の石積堰堤部と，９ｍ長の下流側水叩き部及び護岸部分からなる空積石造建造物が，蔦の細道に通じる散歩道の開放的な自然景観の重要な構成要素となる。工事主任は県技手の大竹弘太。",
  "画像URL": "https://bunka.nii.ac.jp/heritage/43967/_103755/43967_103755111225013231536_300.jpg"
}