{
  "台帳ID": "101",
  "管理対象ID": "00012581",
  "名称": "旧丹治商会門及び煉瓦塀",
  "ふりがな": "きゅうたんじしょうかいれんがべい",
  "員数": "1基",
  "棟名": "きゅうたんじしょうかいれんがべい",
  "文化財種類": "1基",
  "種別1": "",
  "種別2": "登録有形文化財(建造物)",
  "国": "産業3次",
  "時代": "その他工作物",
  "年代": "明治後期／平成29年改修",
  "西暦": "1898～1912",
  "構造及び形式等": "門　石造、間口2.1m　煉瓦塀　煉瓦造、総延長18m",
  "その他参考となるべき事項": "",
  "登録番号": "27 － 0754",
  "登録回": "91",
  "登録告示年月日": "2018.11.02(平成30.11.02)",
  "登録年月日": "2018.11.02(平成30.11.02)",
  "追加年月日": "",
  "重文指定年月日": "",
  "国宝指定年月日": "明治",
  "登録基準1": "国土の歴史的景観に寄与しているもの",
  "登録基準2": "",
  "都道府県": "明治後期／平成29年改修",
  "所在地": "1898～1912",
  "保管施設の名称": "門　石造、間口2.1m　煉瓦塀　煉瓦造、総延長18m",
  "所有者名": "",
  "所有者種別": "営利法人",
  "管理団体又は責任者": "27 － 0754",
  "緯度": "91",
  "経度": "2018.11.02(平成30.11.02)",
  "解説文": "社屋入口正面に立つ石製門とその左右に延び前庭を区切る煉瓦塀。煉瓦塀の正面は煉瓦を千鳥に積んだ透塀で、要所を焼過煉瓦や役物で飾る。両側面は高さ４メートルの高塀で、外観を社屋と調和させる。煉瓦製造を営んだ会社らしく意匠性と堅牢性を兼ね備える。",
  "画像URL": "https://bunka.nii.ac.jp/heritage/43967/_367876/43967_367876338321683824089_300.jpg"
}