{
  "台帳ID": "101",
  "管理対象ID": "00010106",
  "名称": "小林家住宅（旧小武織物有限会社）倉庫一",
  "ふりがな": "こばやしけじゅうたく（きゅうこたけおりものゆうげんがいしゃ）そうこ１",
  "員数": "1棟",
  "棟名": "",
  "文化財種類": "登録有形文化財(建造物)",
  "種別1": "産業2次",
  "種別2": "建築物",
  "国": "",
  "時代": "昭和中",
  "年代": "昭和36",
  "西暦": "1961",
  "構造及び形式等": "コンクリートブロック造平屋建、瓦葺、建築面積21㎡",
  "その他参考となるべき事項": "",
  "登録番号": "10 － 0315",
  "登録回": "78",
  "登録告示年月日": "2014.10.07(平成26.10.07)",
  "登録年月日": "2014.10.07(平成26.10.07)",
  "追加年月日": "",
  "重文指定年月日": "20141007",
  "国宝指定年月日": "",
  "登録基準1": "国土の歴史的景観に寄与しているもの",
  "登録基準2": "",
  "都道府県": "群馬県",
  "所在地": "群馬県桐生市広沢町5字福島1111-9他",
  "保管施設の名称": "",
  "所有者名": "",
  "所有者種別": "",
  "管理団体又は責任者": "",
  "緯度": "36.37920000000000",
  "経度": "139.34960000000000",
  "解説文": "敷地南面東寄りに開く門から西側にのびる石垣上に建つ倉庫。コンクリートブロック造、切妻造桟瓦葺で、西側の下屋に井戸と流し場を設けた。内外壁ともモルタル塗で仕上げ、小屋はトラス組とする。織物の糸の保管や、工場用水と生活用水の確保に使用した建物。",
  "画像URL": "https://bunka.nii.ac.jp/heritage/43967/_197939/43967_197939150317212531985_300.jpg"
}