{
  "台帳ID": "101",
  "管理対象ID": "00013438",
  "名称": "岡橋家住宅南米蔵",
  "ふりがな": "おかはしけじゅうたくみなみこめぐら",
  "員数": "1棟",
  "棟名": "",
  "文化財種類": "登録有形文化財(建造物)",
  "種別1": "住宅",
  "種別2": "建築物",
  "国": "",
  "時代": "昭和前",
  "年代": "昭和前期",
  "西暦": "1926～1945",
  "構造及び形式等": "土蔵造平屋建、瓦葺、建築面積22㎡",
  "その他参考となるべき事項": "",
  "登録番号": "29 － 0311",
  "登録回": "96",
  "登録告示年月日": "2020.08.17(令和2.08.17)",
  "登録年月日": "2020.08.17(令和2.08.17)",
  "追加年月日": "",
  "重文指定年月日": "20200817",
  "国宝指定年月日": "",
  "登録基準1": "国土の歴史的景観に寄与しているもの",
  "登録基準2": "",
  "都道府県": "奈良県",
  "所在地": "奈良県橿原市小槻町586-1",
  "保管施設の名称": "",
  "所有者名": "清光林業株式会社",
  "所有者種別": "営利法人",
  "管理団体又は責任者": "",
  "緯度": "34.53147222000000",
  "経度": "135.77323056000000",
  "解説文": "敷地南東隅に西面して建つ。土蔵造平屋建、桟瓦葺で、窓に持送付小庇を付す。外壁は漆喰で軒裏まで塗込めて軒下に鉢巻３段を廻し、敷地外周の南面、東面の腰を竪板張とする。内部は土間で、壁を大壁中塗、和小屋組とする。長屋門と共に表構の一角を成す。",
  "画像URL": "https://bunka.nii.ac.jp/heritage/43967/_368523/43967_368523999709387985577_300.jpg"
}