{
  "台帳ID": "101",
  "管理対象ID": "00011130",
  "名称": "山縣神社鳥居",
  "ふりがな": "やまがたじんじゃとりい",
  "員数": "1基",
  "棟名": "",
  "文化財種類": "登録有形文化財(建造物)",
  "種別1": "宗教",
  "種別2": "その他工作物",
  "国": "",
  "時代": "大正",
  "年代": "大正12",
  "西暦": "1923",
  "構造及び形式等": "鉄筋コンクリート造、高さ6.8m、間口4.5m",
  "その他参考となるべき事項": "",
  "登録番号": "19 - 0080",
  "登録回": "84",
  "登録告示年月日": "2016.08.01(平成28.08.01)",
  "登録年月日": "2016.08.01(平成28.08.01)",
  "追加年月日": "",
  "重文指定年月日": "20160801",
  "国宝指定年月日": "",
  "登録基準1": "造形の規範となっているもの",
  "登録基準2": "",
  "都道府県": "山梨県",
  "所在地": "山梨県甲斐市篠原190-1",
  "保管施設の名称": "",
  "所有者名": "宗教法人山縣神社",
  "所有者種別": "宗教法人",
  "管理団体又は責任者": "",
  "緯度": "35.65720000000000",
  "経度": "138.52170000000000",
  "解説文": "境内南端の参道入口に建つ。鉄筋コンクリート造、表面モルタル洗出仕上げの神明鳥居で、柱間四・五メートル、高さ六・八メートルの規模を持つ。円柱を掘立柱風に垂直に建て、角材の貫で繋ぎくさびの造形をつくり、丸材の笠木を載せる。近代における鳥居の一例。",
  "画像URL": "https://bunka.nii.ac.jp/heritage/43967/_205237/43967_205237358901821885073_300.jpg"
}