{
  "台帳ID": "101",
  "管理対象ID": "00014020",
  "名称": "高林家住宅平常門及び塀",
  "ふりがな": "たかばやしけじゅうたくへいじょうもんおよびへい",
  "員数": "1棟",
  "棟名": "",
  "文化財種類": "登録有形文化財(建造物)",
  "種別1": "住宅",
  "種別2": "その他工作物",
  "国": "",
  "時代": "昭和前",
  "年代": "昭和8年頃",
  "西暦": "1933",
  "構造及び形式等": "平常門　木造、銅板葺、間口2.7m　塀　木造、延長10m",
  "その他参考となるべき事項": "",
  "登録番号": "22 - 0309",
  "登録回": "0",
  "登録告示年月日": "2021.10.14(令和3.10.14)",
  "登録年月日": "2021.10.14(令和3.10.14)",
  "追加年月日": "",
  "重文指定年月日": "20211014",
  "国宝指定年月日": "",
  "登録基準1": "国土の歴史的景観に寄与しているもの",
  "登録基準2": "",
  "都道府県": "静岡県",
  "所在地": "静岡県浜松市東区有玉南町字宮廻1646-1",
  "保管施設の名称": "",
  "所有者名": "",
  "所有者種別": "",
  "管理団体又は責任者": "",
  "緯度": "34.75144444000000",
  "経度": "137.75213333000000",
  "解説文": "男衆部屋西妻から田舎屋南東角に至る東西塀と、表側区画と主屋の区画を仕切る門。昭和初期に主屋と共に建て替えた。門は切妻造、腕木門、出節柱と引分戸を構える。塀はコンクリート柱の板塀で、裏側を杉皮張とする。旧家の奥深い屋敷構えを形成する。",
  "画像URL": "https://bunka.nii.ac.jp/heritage/43967/_508280/43967_508280311081182282584_300.jpg"
}