{
  "台帳ID": "101",
  "管理対象ID": "00011139",
  "名称": "東山荘本館",
  "ふりがな": "とうざんそうほんかん",
  "員数": "1棟",
  "棟名": "",
  "文化財種類": "登録有形文化財(建造物)",
  "種別1": "住宅",
  "種別2": "建築物",
  "国": "",
  "時代": "昭和前",
  "年代": "昭和8／昭和15増築",
  "西暦": "1933／1940増築",
  "構造及び形式等": "木造2階建、瓦葺一部銅板葺、建築面積240㎡",
  "その他参考となるべき事項": "",
  "登録番号": "22 - 0224",
  "登録回": "84",
  "登録告示年月日": "2016.08.01(平成28.08.01)",
  "登録年月日": "2016.08.01(平成28.08.01)",
  "追加年月日": "",
  "重文指定年月日": "20160801",
  "国宝指定年月日": "",
  "登録基準1": "国土の歴史的景観に寄与しているもの",
  "登録基準2": "",
  "都道府県": "静岡県",
  "所在地": "静岡県熱海市春日町1712-5他",
  "保管施設の名称": "",
  "所有者名": "宗教法人世界救世教",
  "所有者種別": "宗教法人",
  "管理団体又は責任者": "",
  "緯度": "35.10388000000000",
  "経度": "139.08170000000000",
  "解説文": "相模湾を望む敷地北東寄りに位置する。南北廊下の東側中央を二階建として、上下階とも座敷二室に縁を廻らす。下階は北に玄関棟、南に浴室を配する。全体に木柄が細く、数寄屋を加味した繊細な意匠を基調とし、東面は大きなガラス窓をたて、開放感をもたせる。",
  "画像URL": "https://bunka.nii.ac.jp/heritage/43967/_205246/43967_205246297412668975406_300.jpg"
}