{
  "台帳ID": "101",
  "管理対象ID": "00013625",
  "名称": "山﨑家住宅主屋",
  "ふりがな": "やまさきけじゅうたくおもや",
  "員数": "1棟",
  "棟名": "やまさきけじゅうたくおもや",
  "文化財種類": "1棟",
  "種別1": "",
  "種別2": "登録有形文化財(建造物)",
  "国": "住宅",
  "時代": "建築物",
  "年代": "大正6年／平成25年改修",
  "西暦": "1917",
  "構造及び形式等": "木造2階建、瓦葺、建築面積462㎡",
  "その他参考となるべき事項": "",
  "登録番号": "30 － 0295",
  "登録回": "97",
  "登録告示年月日": "2021.02.04(令和3.02.04)",
  "登録年月日": "2021.02.04(令和3.02.04)",
  "追加年月日": "",
  "重文指定年月日": "",
  "国宝指定年月日": "大正",
  "登録基準1": "国土の歴史的景観に寄与しているもの",
  "登録基準2": "",
  "都道府県": "大正6年／平成25年改修",
  "所在地": "1917",
  "保管施設の名称": "木造2階建、瓦葺、建築面積462㎡",
  "所有者名": "",
  "所有者種別": "",
  "管理団体又は責任者": "30 － 0295",
  "緯度": "97",
  "経度": "2021.02.04(令和3.02.04)",
  "解説文": "ＪＲ粉河駅北に敷地を構える。入母屋造の南妻に入母屋造玄関を突出する。東に折上格天井の大広間棟、西に中庭を介して家政棟が接続する。続き間座敷が四組あり趣を異にして上質な造作を見せる。二階八畳は傘天井で飾る。良材を駆使した近代和風住宅である。",
  "画像URL": "https://bunka.nii.ac.jp/heritage/43967/_504994/43967_504994286757366165685_300.jpg"
}