{
  "台帳ID": "101",
  "管理対象ID": "00012431",
  "名称": "土井家住宅主屋",
  "ふりがな": "どいけじゅうたくしゅおく",
  "員数": "1棟",
  "棟名": "",
  "文化財種類": "登録有形文化財(建造物)",
  "種別1": "住宅",
  "種別2": "建築物",
  "国": "",
  "時代": "明治",
  "年代": "明治45年頃／昭和50年代改修",
  "西暦": "1912",
  "構造及び形式等": "木造2階建、瓦葺、建築面積226㎡",
  "その他参考となるべき事項": "",
  "登録番号": "28-688",
  "登録回": "90",
  "登録告示年月日": "2018.05.10(平成30.05.10)",
  "登録年月日": "2018.05.10(平成30.05.10)",
  "追加年月日": "",
  "重文指定年月日": "20180510",
  "国宝指定年月日": "",
  "登録基準1": "国土の歴史的景観に寄与しているもの",
  "登録基準2": "",
  "都道府県": "兵庫県",
  "所在地": "兵庫県姫路市大津区平松字屋敷503",
  "保管施設の名称": "",
  "所有者名": "",
  "所有者種別": "",
  "管理団体又は責任者": "",
  "緯度": "34.79739000000000",
  "経度": "134.60110000000000",
  "解説文": "姫路市郊外の旧平松港で代々多角的に商売を営んだ旧家の住宅。主屋は街路に南面して建ち、正面西半から側面に庭を設ける。入母屋造本瓦葺で、二階正面は開口部として眺望を確保し、両端から側面は漆喰塗で重厚に仕上げる。港町の歴史的景観の核となっている。",
  "画像URL": "https://bunka.nii.ac.jp/heritage/43967/_354552/43967_354552472489898246767_300.jpg"
}